<?xml version="1.0" ?>
<Settings>
  <MultipleSearchAndReplaceList>
    <Group>
            
      <Name>2-1-4.ㅍㅎ</Name>
            
      <Enabled>True</Enabled>
            
      <MultipleSearchAndReplaceItem>
                
        <Enabled>True</Enabled>
                
        <FindWhat>파이오</FindWhat>
                
        <ReplaceWith>펠라</ReplaceWith>
                
        <SearchType>Normal</SearchType>
                
        <Description>ㅍ - 펠라</Description>
              
      </MultipleSearchAndReplaceItem>
            
      <MultipleSearchAndReplaceItem>
                
        <Enabled>True</Enabled>
                
        <FindWhat>빈 빈이잖</FindWhat>
                
        <ReplaceWith>팔팔하잖</ReplaceWith>
                
        <SearchType>RegularExpression</SearchType>
                
        <Description>ㅍ - 팔팔하잖</Description>
              
      </MultipleSearchAndReplaceItem>
            
      <MultipleSearchAndReplaceItem>
                
        <Enabled>True</Enabled>
                
        <FindWhat>빈틈이 많으면</FindWhat>
                
        <ReplaceWith>팔팔해서</ReplaceWith>
                
        <SearchType>RegularExpression</SearchType>
                
        <Description>ㅍ - 팔팔해서</Description>
              
      </MultipleSearchAndReplaceItem>
          
    </Group>
        
  </MultipleSearchAndReplaceList>
</Settings>
